{
  "fuente": "mp",
  "query": "codigo=2345-70-LP26",
  "cacheado_en": 1783090555.640167,
  "payload": {
    "Cantidad": 1,
    "FechaCreacion": "2026-07-03T14:55:55.6244383Z",
    "Version": "v1",
    "Listado": [
      {
        "CodigoExterno": "2345-70-LP26",
        "Nombre": "DISEÑO DE ESPECIALIDADES PROYECTO PARQUE DEPORTIVO",
        "CodigoEstado": 5,
        "Descripcion": "El objetivo de este proceso de licitación es contratar el servicio de elaboración del diseño de las distintas especialidades requeridas para la construcción del nuevo Parque Deportivo, ubicado en Av. Paul Harris Sur 701, Las Condes. \r\nLos servicios del contratista se deberán prestar en 2 etapas:\r\n-\tEtapa N°1: Diseño de especialidades en donde el contratista deberá desarrollar los proyectos de especialidades que se le contraten, en su versión apta para construcción.\r\n-\tEtapa N°2: Acompañamiento en la construcción de la obra, el contratista deberá efectuar el acompañamiento de las obras propias de la ejecución de los proyectos contratados.",
        "FechaCierre": null,
        "Estado": "Publicada",
        "Comprador": {
          "CodigoOrganismo": "86571",
          "NombreOrganismo": "I MUNICIPALIDAD DE LAS CONDES",
          "RutUnidad": "69.070.400-5",
          "CodigoUnidad": "3338",
          "NombreUnidad": "I MUNICIPALIDAD DE LAS CONDES",
          "DireccionUnidad": "Avda. Andres Bello Nº 2.610",
          "ComunaUnidad": "Las Condes",
          "RegionUnidad": "Región Metropolitana de Santiago",
          "RutUsuario": "",
          "CodigoUsuario": "2139425",
          "NombreUsuario": "JAVIERA ANDREA ARANDA ARANEDA",
          "CargoUsuario": "Analista de Compras"
        },
        "DiasCierreLicitacion": "17",
        "Informada": 0,
        "CodigoTipo": 1,
        "Tipo": "LP",
        "TipoConvocatoria": "1",
        "Moneda": "CLF",
        "Etapas": 1,
        "EstadoEtapas": "0",
        "TomaRazon": "0",
        "EstadoPublicidadOfertas": 1,
        "JustificacionPublicidad": "",
        "Contrato": "0",
        "Obras": "0",
        "CantidadReclamos": 130,
        "Fechas": {
          "FechaCreacion": "2026-04-15T00:00:00",
          "FechaCierre": "2026-07-20T15:01:00",
          "FechaInicio": "2026-06-30T13:01:00",
          "FechaFinal": "2026-07-06T12:00:00",
          "FechaPubRespuestas": "2026-07-13T20:00:00",
          "FechaActoAperturaTecnica": "2026-07-20T15:30:00",
          "FechaActoAperturaEconomica": "2026-07-20T15:30:00",
          "FechaPublicacion": "2026-06-30T12:19:06.607",
          "FechaAdjudicacion": "2026-09-21T20:00:00",
          "FechaEstimadaAdjudicacion": "2026-09-21T20:00:00",
          "FechaSoporteFisico": null,
          "FechaTiempoEvaluacion": "1900-01-16T00:00:00",
          "FechaEstimadaFirma": null,
          "FechasUsuario": null,
          "FechaVisitaTerreno": null,
          "FechaEntregaAntecedentes": null
        },
        "UnidadTiempoEvaluacion": 2,
        "DireccionVisita": "",
        "DireccionEntrega": "",
        "Estimacion": 2,
        "FuenteFinanciamiento": "",
        "VisibilidadMonto": 1,
        "MontoEstimado": 3675,
        "Tiempo": "20",
        "UnidadTiempo": "2",
        "Modalidad": 1,
        "TipoPago": "1",
        "NombreResponsablePago": "Tesorería Municipal",
        "EmailResponsablePago": "",
        "NombreResponsableContrato": "Directora de Secretaría Comunal de Planificación",
        "EmailResponsableContrato": "",
        "FonoResponsableContrato": "",
        "ProhibicionContratacion": "",
        "SubContratacion": "1",
        "UnidadTiempoDuracionContrato": 4,
        "TiempoDuracionContrato": "20",
        "TipoDuracionContrato": " ",
        "JustificacionMontoEstimado": "La contratación se estructurará bajo la modalidad de SUMA ALZADA, por cada uno de los proyectos individualizados en el Anexo N°3, los cuales se encuentran debidamente definidos en las Bases Técnicas y demás antecedentes de la licitación.",
        "ObservacionContract": null,
        "ExtensionPlazo": 0,
        "EsBaseTipo": 0,
        "UnidadTiempoContratoLicitacion": "2",
        "ValorTiempoRenovacion": "0",
        "PeriodoTiempoRenovacion": " ",
        "EsRenovable": 0,
        "CodigoBIP": null,
        "Adjudicacion": null,
        "Items": {
          "Cantidad": 1,
          "Listado": [
            {
              "Correlativo": 1,
              "CodigoProducto": 80111614,
              "CodigoCategoria": "80111600",
              "Categoria": "Servicios profesionales, administrativos y consultorías de gestión empresarial / Servicios de recursos humanos / Servicios de personal temporal",
              "NombreProducto": "Servicios temporales de ingeniería",
              "Descripcion": "Anexo N°3 \"Oferta Económica\" - OFERTA ECONÓMICA NETA (Sumatoria Columna C). ",
              "UnidadMedida": "Unidad",
              "Cantidad": 1,
              "Adjudicacion": null
            }
          ]
        }
      }
    ]
  }
}