{
  "fuente": "mp",
  "query": "codigo=1057501-412-LR26",
  "cacheado_en": 1783430742.481109,
  "payload": {
    "Cantidad": 1,
    "FechaCreacion": "2026-07-07T13:25:42.5164849Z",
    "Version": "v1",
    "Listado": [
      {
        "CodigoExterno": "1057501-412-LR26",
        "Nombre": "CONVENIO PRÓTESIS DE RODILLA COMPLEJA",
        "CodigoEstado": 5,
        "Descripcion": "El Hospital Dr. Sótero del Río, mediante licitación pública, requiere contar con \tEQUIPO DE RODILLA CONVENIO SUMINISTRO INSUMOS PROTESIS DE RODILLAS COMPLEJAS a fin de brindar oportuna prestación asistencial a los pacientes del HSR, por un periodo de 36 meses.",
        "FechaCierre": null,
        "Estado": "Publicada",
        "Comprador": {
          "CodigoOrganismo": "7320",
          "NombreOrganismo": "COMPLEJO ASISTENCIAL DR. SOTERO DEL RIO",
          "RutUnidad": "61.608.502-6",
          "CodigoUnidad": "1057501",
          "NombreUnidad": "COMPLEJO ASISTENCIAL DR. SOTERO DEL RIO",
          "DireccionUnidad": "Avenida Melchor  Concha y Toro 3459, Puente Alto",
          "ComunaUnidad": "Puente Alto",
          "RegionUnidad": "Región Metropolitana de Santiago",
          "RutUsuario": "",
          "CodigoUsuario": "1210914",
          "NombreUsuario": "Francisco Manzo",
          "CargoUsuario": "Supervisor Insumos Clínicos y Prótesis"
        },
        "DiasCierreLicitacion": "30",
        "Informada": 0,
        "CodigoTipo": 1,
        "Tipo": "LR",
        "TipoConvocatoria": "1",
        "Moneda": "CLP",
        "Etapas": 1,
        "EstadoEtapas": "0",
        "TomaRazon": "0",
        "EstadoPublicidadOfertas": 1,
        "JustificacionPublicidad": "",
        "Contrato": "0",
        "Obras": "0",
        "CantidadReclamos": 5483,
        "Fechas": {
          "FechaCreacion": "2026-06-30T00:00:00",
          "FechaCierre": "2026-08-06T16:39:00",
          "FechaInicio": "2026-07-06T20:40:00",
          "FechaFinal": "2026-07-16T20:40:00",
          "FechaPubRespuestas": "2026-07-17T20:40:00",
          "FechaActoAperturaTecnica": "2026-08-06T16:40:00",
          "FechaActoAperturaEconomica": "2026-08-06T16:40:00",
          "FechaPublicacion": "2026-07-06T13:27:55.383",
          "FechaAdjudicacion": "2026-08-25T16:40:00",
          "FechaEstimadaAdjudicacion": "2026-08-25T16:40:00",
          "FechaSoporteFisico": null,
          "FechaTiempoEvaluacion": null,
          "FechaEstimadaFirma": null,
          "FechasUsuario": null,
          "FechaVisitaTerreno": null,
          "FechaEntregaAntecedentes": null
        },
        "UnidadTiempoEvaluacion": 1,
        "DireccionVisita": "",
        "DireccionEntrega": "",
        "Estimacion": 1,
        "FuenteFinanciamiento": "",
        "VisibilidadMonto": 0,
        "MontoEstimado": null,
        "Tiempo": "36",
        "UnidadTiempo": "1",
        "Modalidad": 1,
        "TipoPago": "2",
        "NombreResponsablePago": "RAMON VARAS RODRIGUEZ",
        "EmailResponsablePago": "",
        "NombreResponsableContrato": "FRANCISCO MANZO VILLALOBOS",
        "EmailResponsableContrato": "",
        "FonoResponsableContrato": "",
        "ProhibicionContratacion": "Sólo se acepta en el traslado de los productos.",
        "SubContratacion": "0",
        "UnidadTiempoDuracionContrato": 4,
        "TiempoDuracionContrato": "36",
        "TipoDuracionContrato": " ",
        "JustificacionMontoEstimado": "",
        "ObservacionContract": null,
        "ExtensionPlazo": 0,
        "EsBaseTipo": 0,
        "UnidadTiempoContratoLicitacion": "2",
        "ValorTiempoRenovacion": "0",
        "PeriodoTiempoRenovacion": " ",
        "EsRenovable": 0,
        "CodigoBIP": null,
        "Adjudicacion": null,
        "Items": {
          "Cantidad": 31,
          "Listado": [
            {
              "Correlativo": 1,
              "CodigoProducto": 42242003,
              "CodigoCategoria": "42242000",
              "Categoria": "Equipamiento y suministros médicos / Productos medicinales para deportes, prostéticos y ortopédicos / Dispositivos, accesorios y suministros protésicos",
              "NombreProducto": "Dispositivos de sujeción protésica o accesorios",
              "Descripcion": "21-345-200-033-00   ADAPTADOR DE DESPLAZAMIENTO PARA RODILLA\r\n",
              "UnidadMedida": "Unidad",
              "Cantidad": 1,
              "Adjudicacion": null
            },
            {
              "Correlativo": 2,
              "CodigoProducto": 42242003,
              "CodigoCategoria": "42242000",
              "Categoria": "Equipamiento y suministros médicos / Productos medicinales para deportes, prostéticos y ortopédicos / Dispositivos, accesorios y suministros protésicos",
              "NombreProducto": "Dispositivos de sujeción protésica o accesorios",
              "Descripcion": "21-345-200-034-00   ADAPTADOR DE DESPLAZAMIENTO PARA VASTAGOS RODILLA MODULAR\r\n",
              "UnidadMedida": "Unidad",
              "Cantidad": 1,
              "Adjudicacion": null
            },
            {
              "Correlativo": 3,
              "CodigoProducto": 42242003,
              "CodigoCategoria": "42242000",
              "Categoria": "Equipamiento y suministros médicos / Productos medicinales para deportes, prostéticos y ortopédicos / Dispositivos, accesorios y suministros protésicos",
              "NombreProducto": "Dispositivos de sujeción protésica o accesorios",
              "Descripcion": "21-345-200-035-00   AUMENTO TIBIAL PARA RODILLA FIJA\r\n",
              "UnidadMedida": "Unidad",
              "Cantidad": 1,
              "Adjudicacion": null
            },
            {
              "Correlativo": 4,
              "CodigoProducto": 42242003,
              "CodigoCategoria": "42242000",
              "Categoria": "Equipamiento y suministros médicos / Productos medicinales para deportes, prostéticos y ortopédicos / Dispositivos, accesorios y suministros protésicos",
              "NombreProducto": "Dispositivos de sujeción protésica o accesorios",
              "Descripcion": "21-345-200-036-00   COMPONENTE FEMORAL CEMENTADO RODILLA \r\n",
              "UnidadMedida": "Unidad",
              "Cantidad": 1,
              "Adjudicacion": null
            },
            {
              "Correlativo": 5,
              "CodigoProducto": 42242003,
              "CodigoCategoria": "42242000",
              "Categoria": "Equipamiento y suministros médicos / Productos medicinales para deportes, prostéticos y ortopédicos / Dispositivos, accesorios y suministros protésicos",
              "NombreProducto": "Dispositivos de sujeción protésica o accesorios",
              "Descripcion": "21-345-200-037-00   COMPONENTE FEMORAL CEMENTADO RODILLA POSTERIOR ESTABILIZADA\r\n",
              "UnidadMedida": "Unidad",
              "Cantidad": 1,
              "Adjudicacion": null
            },
            {
              "Correlativo": 6,
              "CodigoProducto": 42242003,
              "CodigoCategoria": "42242000",
              "Categoria": "Equipamiento y suministros médicos / Productos medicinales para deportes, prostéticos y ortopédicos / Dispositivos, accesorios y suministros protésicos",
              "NombreProducto": "Dispositivos de sujeción protésica o accesorios",
              "Descripcion": "21-345-200-038-00   COMPONENTE FEMORAL CEMENTADO RODILLA POSTERIOR ESTABILIZADA CON REC DE NITRURO DE TITANIO\r\n",
              "UnidadMedida": "Unidad",
              "Cantidad": 1,
              "Adjudicacion": null
            },
            {
              "Correlativo": 7,
              "CodigoProducto": 42242003,
              "CodigoCategoria": "42242000",
              "Categoria": "Equipamiento y suministros médicos / Productos medicinales para deportes, prostéticos y ortopédicos / Dispositivos, accesorios y suministros protésicos",
              "NombreProducto": "Dispositivos de sujeción protésica o accesorios",
              "Descripcion": "21-345-200-039-00   COMPONENTE FEMORAL CEMENTADO RODILLA SEMICONSTREÑIDA CON REC DE NITRURO DE TITANIO\r\n",
              "UnidadMedida": "Unidad",
              "Cantidad": 1,
              "Adjudicacion": null
            },
            {
              "Correlativo": 8,
              "CodigoProducto": 42242003,
              "CodigoCategoria": "42242000",
              "Categoria": "Equipamiento y suministros médicos / Productos medicinales para deportes, prostéticos y ortopédicos / Dispositivos, accesorios y suministros protésicos",
              "NombreProducto": "Dispositivos de sujeción protésica o accesorios",
              "Descripcion": "21-345-200-040-00   COMPONENTE FEMORAL CEMENTADO RODILLA UNI MOVIL\r\n",
              "UnidadMedida": "Unidad",
              "Cantidad": 1,
              "Adjudicacion": null
            },
            {
              "Correlativo": 9,
              "CodigoProducto": 42242003,
              "CodigoCategoria": "42242000",
              "Categoria": "Equipamiento y suministros médicos / Productos medicinales para deportes, prostéticos y ortopédicos / Dispositivos, accesorios y suministros protésicos",
              "NombreProducto": "Dispositivos de sujeción protésica o accesorios",
              "Descripcion": "21-345-200-041-00   COMPONENTE TIBIAL CEMENTADO RODILLA FIJO\r\n",
              "UnidadMedida": "Unidad",
              "Cantidad": 1,
              "Adjudicacion": null
            },
            {
              "Correlativo": 10,
              "CodigoProducto": 42242003,
              "CodigoCategoria": "42242000",
              "Categoria": "Equipamiento y suministros médicos / Productos medicinales para deportes, prostéticos y ortopédicos / Dispositivos, accesorios y suministros protésicos",
              "NombreProducto": "Dispositivos de sujeción protésica o accesorios",
              "Descripcion": "21-345-200-042-00   COMPONENTE TIBIAL CEMENTADO RODILLA FIJO\r\n",
              "UnidadMedida": "Unidad",
              "Cantidad": 1,
              "Adjudicacion": null
            },
            {
              "Correlativo": 11,
              "CodigoProducto": 42242003,
              "CodigoCategoria": "42242000",
              "Categoria": "Equipamiento y suministros médicos / Productos medicinales para deportes, prostéticos y ortopédicos / Dispositivos, accesorios y suministros protésicos",
              "NombreProducto": "Dispositivos de sujeción protésica o accesorios",
              "Descripcion": "21-345-200-043-00   COMPONENTE TIBIAL CEMENTADO RODILLA FIJO CON REC DE NITRURO DE TITANIO\r\n",
              "UnidadMedida": "Unidad",
              "Cantidad": 1,
              "Adjudicacion": null
            },
            {
              "Correlativo": 12,
              "CodigoProducto": 42242003,
              "CodigoCategoria": "42242000",
              "Categoria": "Equipamiento y suministros médicos / Productos medicinales para deportes, prostéticos y ortopédicos / Dispositivos, accesorios y suministros protésicos",
              "NombreProducto": "Dispositivos de sujeción protésica o accesorios",
              "Descripcion": "21-345-200-044-00   COMPONENTE TIBIAL CEMENTADO RODILLA FIJO CON REC DE NITRURO DE TITANIO\r\n",
              "UnidadMedida": "Unidad",
              "Cantidad": 1,
              "Adjudicacion": null
            },
            {
              "Correlativo": 13,
              "CodigoProducto": 42242003,
              "CodigoCategoria": "42242000",
              "Categoria": "Equipamiento y suministros médicos / Productos medicinales para deportes, prostéticos y ortopédicos / Dispositivos, accesorios y suministros protésicos",
              "NombreProducto": "Dispositivos de sujeción protésica o accesorios",
              "Descripcion": "21-345-200-045-00   COMPONENTE TIBIAL CEMENTADO RODILLA MOVIL CON REC DE NITRURO DE TITANIO\r\n",
              "UnidadMedida": "Unidad",
              "Cantidad": 1,
              "Adjudicacion": null
            },
            {
              "Correlativo": 14,
              "CodigoProducto": 42242003,
              "CodigoCategoria": "42242000",
              "Categoria": "Equipamiento y suministros médicos / Productos medicinales para deportes, prostéticos y ortopédicos / Dispositivos, accesorios y suministros protésicos",
              "NombreProducto": "Dispositivos de sujeción protésica o accesorios",
              "Descripcion": "21-345-200-046-00   COMPONENTE TIBIAL CEMENTADO RODILLA UNI FIJA\r\n",
              "UnidadMedida": "Unidad",
              "Cantidad": 1,
              "Adjudicacion": null
            },
            {
              "Correlativo": 15,
              "CodigoProducto": 42242003,
              "CodigoCategoria": "42242000",
              "Categoria": "Equipamiento y suministros médicos / Productos medicinales para deportes, prostéticos y ortopédicos / Dispositivos, accesorios y suministros protésicos",
              "NombreProducto": "Dispositivos de sujeción protésica o accesorios",
              "Descripcion": "21-345-200-047-00   INSERTO DE POLIETILENO RODILLA FIJO\r\n",
              "UnidadMedida": "Unidad",
              "Cantidad": 1,
              "Adjudicacion": null
            },
            {
              "Correlativo": 16,
              "CodigoProducto": 42242003,
              "CodigoCategoria": "42242000",
              "Categoria": "Equipamiento y suministros médicos / Productos medicinales para deportes, prostéticos y ortopédicos / Dispositivos, accesorios y suministros protésicos",
              "NombreProducto": "Dispositivos de sujeción protésica o accesorios",
              "Descripcion": "21-345-200-048-00   INSERTO DE POLIETILENO RODILLA FIJO HIPERFLEXIBLE\r\n",
              "UnidadMedida": "Unidad",
              "Cantidad": 1,
              "Adjudicacion": null
            },
            {
              "Correlativo": 17,
              "CodigoProducto": 42242003,
              "CodigoCategoria": "42242000",
              "Categoria": "Equipamiento y suministros médicos / Productos medicinales para deportes, prostéticos y ortopédicos / Dispositivos, accesorios y suministros protésicos",
              "NombreProducto": "Dispositivos de sujeción protésica o accesorios",
              "Descripcion": "21-345-200-049-00   INSERTO DE POLIETILENO RODILLA FIJO POSTERIOR ESTABILIZADA HIPERFLEXIBLE\r\n",
              "UnidadMedida": "Unidad",
              "Cantidad": 1,
              "Adjudicacion": null
            },
            {
              "Correlativo": 18,
              "CodigoProducto": 42242003,
              "CodigoCategoria": "42242000",
              "Categoria": "Equipamiento y suministros médicos / Productos medicinales para deportes, prostéticos y ortopédicos / Dispositivos, accesorios y suministros protésicos",
              "NombreProducto": "Dispositivos de sujeción protésica o accesorios",
              "Descripcion": "21-345-200-050-00   INSERTO DE POLIETILENO RODILLA FIJO POSTERIOR ESTABILIZADA HIPERFLEXIBLE ALTAMENTE CRUZADO\r\n",
              "UnidadMedida": "Unidad",
              "Cantidad": 1,
              "Adjudicacion": null
            },
            {
              "Correlativo": 19,
              "CodigoProducto": 42242003,
              "CodigoCategoria": "42242000",
              "Categoria": "Equipamiento y suministros médicos / Productos medicinales para deportes, prostéticos y ortopédicos / Dispositivos, accesorios y suministros protésicos",
              "NombreProducto": "Dispositivos de sujeción protésica o accesorios",
              "Descripcion": "21-345-200-051-00   INSERTO DE POLIETILENO RODILLA FIJO SEMI CONSTREÑIDO\r\n",
              "UnidadMedida": "Unidad",
              "Cantidad": 1,
              "Adjudicacion": null
            },
            {
              "Correlativo": 20,
              "CodigoProducto": 42242003,
              "CodigoCategoria": "42242000",
              "Categoria": "Equipamiento y suministros médicos / Productos medicinales para deportes, prostéticos y ortopédicos / Dispositivos, accesorios y suministros protésicos",
              "NombreProducto": "Dispositivos de sujeción protésica o accesorios",
              "Descripcion": "21-345-200-052-00   INSERTO DE POLIETILENO RODILLA FIJO SEMI CONSTREÑIDO\r\n",
              "UnidadMedida": "Unidad",
              "Cantidad": 1,
              "Adjudicacion": null
            },
            {
              "Correlativo": 21,
              "CodigoProducto": 42242003,
              "CodigoCategoria": "42242000",
              "Categoria": "Equipamiento y suministros médicos / Productos medicinales para deportes, prostéticos y ortopédicos / Dispositivos, accesorios y suministros protésicos",
              "NombreProducto": "Dispositivos de sujeción protésica o accesorios",
              "Descripcion": "21-345-200-053-00   INSERTO DE POLIETILENO RODILLA FIJO ULTRA\r\n",
              "UnidadMedida": "Unidad",
              "Cantidad": 1,
              "Adjudicacion": null
            },
            {
              "Correlativo": 22,
              "CodigoProducto": 42242003,
              "CodigoCategoria": "42242000",
              "Categoria": "Equipamiento y suministros médicos / Productos medicinales para deportes, prostéticos y ortopédicos / Dispositivos, accesorios y suministros protésicos",
              "NombreProducto": "Dispositivos de sujeción protésica o accesorios",
              "Descripcion": "21-345-200-054-00   INSERTO DE POLIETILENO RODILLA MOVIL POSTERIOR ESTABILIZADA HIPERFLEXIBLE\r\n",
              "UnidadMedida": "Unidad",
              "Cantidad": 1,
              "Adjudicacion": null
            },
            {
              "Correlativo": 23,
              "CodigoProducto": 42242003,
              "CodigoCategoria": "42242000",
              "Categoria": "Equipamiento y suministros médicos / Productos medicinales para deportes, prostéticos y ortopédicos / Dispositivos, accesorios y suministros protésicos",
              "NombreProducto": "Dispositivos de sujeción protésica o accesorios",
              "Descripcion": "21-345-200-055-00   INSERTO DE POLIETILENO RODILLA MOVIL POSTERIOR ESTABILIZADA HIPERFLEXIBLE\r\n",
              "UnidadMedida": "Unidad",
              "Cantidad": 1,
              "Adjudicacion": null
            },
            {
              "Correlativo": 24,
              "CodigoProducto": 42242003,
              "CodigoCategoria": "42242000",
              "Categoria": "Equipamiento y suministros médicos / Productos medicinales para deportes, prostéticos y ortopédicos / Dispositivos, accesorios y suministros protésicos",
              "NombreProducto": "Dispositivos de sujeción protésica o accesorios",
              "Descripcion": "21-345-200-056-00   INSERTO DE POLIETILENO UNI FIJO\r\n",
              "UnidadMedida": "Unidad",
              "Cantidad": 1,
              "Adjudicacion": null
            },
            {
              "Correlativo": 25,
              "CodigoProducto": 42242003,
              "CodigoCategoria": "42242000",
              "Categoria": "Equipamiento y suministros médicos / Productos medicinales para deportes, prostéticos y ortopédicos / Dispositivos, accesorios y suministros protésicos",
              "NombreProducto": "Dispositivos de sujeción protésica o accesorios",
              "Descripcion": "21-345-200-057-00   INSERTO DE POLIETILENO UNI FIJO ALTAMENTE CRUZADO VITAMINA E\r\n",
              "UnidadMedida": "Unidad",
              "Cantidad": 1,
              "Adjudicacion": null
            },
            {
              "Correlativo": 26,
              "CodigoProducto": 42242003,
              "CodigoCategoria": "42242000",
              "Categoria": "Equipamiento y suministros médicos / Productos medicinales para deportes, prostéticos y ortopédicos / Dispositivos, accesorios y suministros protésicos",
              "NombreProducto": "Dispositivos de sujeción protésica o accesorios",
              "Descripcion": "21-345-200-058-00   INSERTO DE POLIETILENO UNI MOVIL\r\n",
              "UnidadMedida": "Unidad",
              "Cantidad": 1,
              "Adjudicacion": null
            },
            {
              "Correlativo": 27,
              "CodigoProducto": 42242003,
              "CodigoCategoria": "42242000",
              "Categoria": "Equipamiento y suministros médicos / Productos medicinales para deportes, prostéticos y ortopédicos / Dispositivos, accesorios y suministros protésicos",
              "NombreProducto": "Dispositivos de sujeción protésica o accesorios",
              "Descripcion": "21-345-200-059-00   ROTULA CEMENTADA DE POLIETILENO PARA RODILLA\r\n",
              "UnidadMedida": "Unidad",
              "Cantidad": 1,
              "Adjudicacion": null
            },
            {
              "Correlativo": 28,
              "CodigoProducto": 42242003,
              "CodigoCategoria": "42242000",
              "Categoria": "Equipamiento y suministros médicos / Productos medicinales para deportes, prostéticos y ortopédicos / Dispositivos, accesorios y suministros protésicos",
              "NombreProducto": "Dispositivos de sujeción protésica o accesorios",
              "Descripcion": "21-345-200-060-00   VASTAGO CEMENTADO RODILLA\r\n",
              "UnidadMedida": "Unidad",
              "Cantidad": 1,
              "Adjudicacion": null
            },
            {
              "Correlativo": 29,
              "CodigoProducto": 42242003,
              "CodigoCategoria": "42242000",
              "Categoria": "Equipamiento y suministros médicos / Productos medicinales para deportes, prostéticos y ortopédicos / Dispositivos, accesorios y suministros protésicos",
              "NombreProducto": "Dispositivos de sujeción protésica o accesorios",
              "Descripcion": "21-345-200-061-00   VASTAGO DE EXTENSION RODILLA\r\n",
              "UnidadMedida": "Unidad",
              "Cantidad": 1,
              "Adjudicacion": null
            },
            {
              "Correlativo": 30,
              "CodigoProducto": 42242003,
              "CodigoCategoria": "42242000",
              "Categoria": "Equipamiento y suministros médicos / Productos medicinales para deportes, prostéticos y ortopédicos / Dispositivos, accesorios y suministros protésicos",
              "NombreProducto": "Dispositivos de sujeción protésica o accesorios",
              "Descripcion": "21-345-200-062-00   VASTAGO DE EXTENSION RODILLA 14/25MM. NITRURO DE TITANIO\r\n",
              "UnidadMedida": "Unidad",
              "Cantidad": 1,
              "Adjudicacion": null
            },
            {
              "Correlativo": 31,
              "CodigoProducto": 42242003,
              "CodigoCategoria": "42242000",
              "Categoria": "Equipamiento y suministros médicos / Productos medicinales para deportes, prostéticos y ortopédicos / Dispositivos, accesorios y suministros protésicos",
              "NombreProducto": "Dispositivos de sujeción protésica o accesorios",
              "Descripcion": "21-345-200-063-00   VASTAGO NO CEMENTADO HA RODILLA\r\n",
              "UnidadMedida": "Unidad",
              "Cantidad": 1,
              "Adjudicacion": null
            }
          ]
        }
      }
    ]
  }
}