{
  "fuente": "mp",
  "query": "codigo=1951-29-L126",
  "cacheado_en": 1783431019.0619662,
  "payload": {
    "Cantidad": 1,
    "FechaCreacion": "2026-07-07T13:30:19.0167145Z",
    "Version": "v1",
    "Listado": [
      {
        "CodigoExterno": "1951-29-L126",
        "Nombre": "MANTENIMIENTO CORRECTIVO CON PUESTA EN MARCHA DE UPS",
        "CodigoEstado": 5,
        "Descripcion": "Se requeire efectuar mantenimiento correctivo, con puesta en marcha de 2 dispositivos UPS KEOR-T 10 KVA de 60 baterias de 12 V 9 AH c/u. Especificamente se requiere:\n- Cambio de todas las baterias (nuevas)\n- Limpieza Interna y Externa\n- Eliminacion de códigos de error y/o de mantenimiento\n- Eliminacion de baterias que presente fuga de liquido o daño fisico evidente.\n- Puesta en marcha de cada equipo (100% operativo)\n- Capacitacion funcionarios en principios de funcionamiento y Mtto preventivo.",
        "FechaCierre": null,
        "Estado": "Publicada",
        "Comprador": {
          "CodigoOrganismo": "7131",
          "NombreOrganismo": "SERVICIO DE SALUD ARAUCANIA SUR HOSPITAL CARAHUE",
          "RutUnidad": "61.602.246-6",
          "CodigoUnidad": "2946",
          "NombreUnidad": "Hospital Carahue",
          "DireccionUnidad": "Avda. Alcalde Floody N°",
          "ComunaUnidad": "Carahue",
          "RegionUnidad": "Región de la Araucanía ",
          "RutUsuario": "",
          "CodigoUsuario": "253230",
          "NombreUsuario": "Carlos Patricio Jara Ansorena",
          "CargoUsuario": "Adminitrador"
        },
        "DiasCierreLicitacion": "7",
        "Informada": 0,
        "CodigoTipo": 1,
        "Tipo": "L1",
        "TipoConvocatoria": "1",
        "Moneda": "CLP",
        "Etapas": 1,
        "EstadoEtapas": "0",
        "TomaRazon": "0",
        "EstadoPublicidadOfertas": 1,
        "JustificacionPublicidad": "Todas las ofertas técnicas serán visibles al público en general, través del portal www.mercadopublico.cl, desde el momento de la apertura electrónica.",
        "Contrato": "0",
        "Obras": "0",
        "CantidadReclamos": 54,
        "Fechas": {
          "FechaCreacion": "2026-07-03T15:13:09.687",
          "FechaCierre": "2026-07-14T21:06:00",
          "FechaInicio": "2026-07-03T19:19:26.797",
          "FechaFinal": "2026-07-08T21:06:00",
          "FechaPubRespuestas": "2026-07-09T21:06:00",
          "FechaActoAperturaTecnica": "2026-07-15T21:00:00",
          "FechaActoAperturaEconomica": "2026-07-15T21:00:00",
          "FechaPublicacion": "2026-07-03T19:19:26.797",
          "FechaAdjudicacion": "2026-07-17T21:06:00",
          "FechaEstimadaAdjudicacion": "2026-07-17T21:06:00",
          "FechaSoporteFisico": null,
          "FechaTiempoEvaluacion": null,
          "FechaEstimadaFirma": null,
          "FechasUsuario": null,
          "FechaVisitaTerreno": null,
          "FechaEntregaAntecedentes": null
        },
        "UnidadTiempoEvaluacion": 2,
        "DireccionVisita": "",
        "DireccionEntrega": "",
        "Estimacion": 2,
        "FuenteFinanciamiento": "",
        "VisibilidadMonto": 1,
        "MontoEstimado": 4000000,
        "Tiempo": null,
        "UnidadTiempo": "2",
        "Modalidad": 0,
        "TipoPago": "-1",
        "NombreResponsablePago": "",
        "EmailResponsablePago": "",
        "NombreResponsableContrato": "",
        "EmailResponsableContrato": "",
        "FonoResponsableContrato": "",
        "ProhibicionContratacion": "",
        "SubContratacion": "1",
        "UnidadTiempoDuracionContrato": 0,
        "TiempoDuracionContrato": "0",
        "TipoDuracionContrato": " ",
        "JustificacionMontoEstimado": "1",
        "ObservacionContract": null,
        "ExtensionPlazo": 0,
        "EsBaseTipo": 0,
        "UnidadTiempoContratoLicitacion": "0",
        "ValorTiempoRenovacion": "0",
        "PeriodoTiempoRenovacion": " ",
        "EsRenovable": 0,
        "CodigoBIP": null,
        "Adjudicacion": null,
        "Items": {
          "Cantidad": 1,
          "Listado": [
            {
              "Correlativo": 1,
              "CodigoProducto": 72102201,
              "CodigoCategoria": "72102200",
              "Categoria": "Servicios de construcción y mantenimiento / Servicios de atención, mantenimiento y reparaciones de edificios / Servicios eléctricos",
              "NombreProducto": "Instalación o servicio de sistemas de energía eléctrica",
              "Descripcion": "Mantenimiento Corretivo 2 UPS KEOR-T 10KVA compuesta c/u por 60 baterias 12V 9AH (con puesta en marcha)",
              "UnidadMedida": "Unidad",
              "Cantidad": 2,
              "Adjudicacion": null
            }
          ]
        }
      }
    ]
  }
}