{
  "fuente": "mp",
  "query": "codigo=1549-56-LP26",
  "cacheado_en": 1783090097.660005,
  "payload": {
    "Cantidad": 1,
    "FechaCreacion": "2026-07-03T14:48:17.6248561Z",
    "Version": "v1",
    "Listado": [
      {
        "CodigoExterno": "1549-56-LP26",
        "Nombre": "ADQ INSUMOS PARA LA UNIDAD DE ENDOSCOPIA DEL HSJ",
        "CodigoEstado": 5,
        "Descripcion": "1º\tQue, al Ministerio de Salud le compete ejercer la función que corresponde al Estado de garantizar el libre e igualitario acceso a las acciones de promoción, protección y recuperación de la salud y de rehabilitación de la persona enferma; así como coordinar, controlar y, cuando corresponda, ejecutar tales acciones. Por su parte, el Hospital San José es un Establecimiento de Autogestión en Red, funcionalmente desconcentrado, que tiene por misión ejercer las acciones de salud que le han sido encomendadas.\r\n2.\tQue, de acuerdo con lo establecido en la Resolución Exenta N° 443, de fecha 26 de enero de 2026, que aprueba Plan Anual de Compras y Contrataciones año 2026 para el Complejo Hospitalario San José, se requiere la adquisición de insumos para la unidad de Endoscopia. Lo anterior, según consta en el certificado de fecha 09 de abril de 2026, de la Unidad de Abastecimiento. \r\n\r\n3.\tQue los bienes requeridos, no se encuentran en el Catálogo del Convenio Marco, dispuesto en el Sistema de Información y Gestión de Compras y Contrataciones del Estado, según da cuenta certificado emitido por la jefatura de Adquisiciones del Hospital San José, de fecha 09 de abril de 2026, en conformidad con lo dispuesto en el artículo 35 bis, inciso segundo, de la Ley N°19.886 y en el artículo 29 del reglamento de la ley de compras.\r\n\r\n4.\tQue, tratándose de bienes que, por su naturaleza, no pueden ser reutilizados ni compartidos, atendido a lo dispuesto en el artículo 28, inciso segundo, del reglamento de la ley de compras, el Hospital San José se encuentra exento del procedimiento de consulta a la plataforma de economía circular.\r\n\r\n5.\tQue, conforme con lo prescrito en el artículo 9° de la Ley N° 18.575, ley orgánica constitucional de bases generales de la Administración del Estado, los contratos administrativos se celebrarán previa propuesta pública; por su parte, el artículo 5° de la Ley N° 19.886, ley de bases sobre contratos administrativos de suministro y prestación de servicios, dispone que la Administración adjudicará los contratos que celebre mediante licitación pública; por último, según prescribe el artículo 29° del reglamento de la ley de compras, procede la licitación pública cuando no proceda la contratación a través de convenio marco.",
        "FechaCierre": null,
        "Estado": "Publicada",
        "Comprador": {
          "CodigoOrganismo": "7406",
          "NombreOrganismo": "SERVICIO DE SALUD METROPOLITANA NORTE HOSPITAL SAN JOSE",
          "RutUnidad": "61.608.002-4",
          "CodigoUnidad": "2545",
          "NombreUnidad": "Hospital San  José",
          "DireccionUnidad": "San José 1196",
          "ComunaUnidad": "Independencia",
          "RegionUnidad": "Región Metropolitana de Santiago",
          "RutUsuario": "",
          "CodigoUsuario": "1577130",
          "NombreUsuario": "FABIOLA ELIZABETH CORNEJO BRAVO",
          "CargoUsuario": "EJECUTIVA DE LICITACIONES"
        },
        "DiasCierreLicitacion": "17",
        "Informada": 0,
        "CodigoTipo": 1,
        "Tipo": "LP",
        "TipoConvocatoria": "1",
        "Moneda": "CLP",
        "Etapas": 1,
        "EstadoEtapas": "0",
        "TomaRazon": "0",
        "EstadoPublicidadOfertas": 1,
        "JustificacionPublicidad": "",
        "Contrato": "0",
        "Obras": "0",
        "CantidadReclamos": 3652,
        "Fechas": {
          "FechaCreacion": "2026-06-23T10:31:28.423",
          "FechaCierre": "2026-07-20T15:04:00",
          "FechaInicio": "2026-06-25T12:33:00",
          "FechaFinal": "2026-06-30T15:00:00",
          "FechaPubRespuestas": "2026-07-10T23:59:00",
          "FechaActoAperturaTecnica": "2026-07-20T15:05:00",
          "FechaActoAperturaEconomica": "2026-07-20T15:05:00",
          "FechaPublicacion": "2026-06-25T09:24:01.467",
          "FechaAdjudicacion": "2026-09-21T15:05:00",
          "FechaEstimadaAdjudicacion": "2026-09-21T15:05:00",
          "FechaSoporteFisico": null,
          "FechaTiempoEvaluacion": null,
          "FechaEstimadaFirma": null,
          "FechasUsuario": "1900-01-02T00:00:00",
          "FechaVisitaTerreno": null,
          "FechaEntregaAntecedentes": null
        },
        "UnidadTiempoEvaluacion": 1,
        "DireccionVisita": "",
        "DireccionEntrega": "",
        "Estimacion": 1,
        "FuenteFinanciamiento": "Tesoreria General de la Republica",
        "VisibilidadMonto": 1,
        "MontoEstimado": 304000000,
        "Tiempo": "24",
        "UnidadTiempo": "1",
        "Modalidad": 1,
        "TipoPago": "1",
        "NombreResponsablePago": "Hospital San Jose",
        "EmailResponsablePago": "",
        "NombreResponsableContrato": "Diego Vallejos",
        "EmailResponsableContrato": "",
        "FonoResponsableContrato": "",
        "ProhibicionContratacion": "",
        "SubContratacion": "1",
        "UnidadTiempoDuracionContrato": 4,
        "TiempoDuracionContrato": "24",
        "TipoDuracionContrato": " ",
        "JustificacionMontoEstimado": "",
        "ObservacionContract": null,
        "ExtensionPlazo": 0,
        "EsBaseTipo": 0,
        "UnidadTiempoContratoLicitacion": "2",
        "ValorTiempoRenovacion": "0",
        "PeriodoTiempoRenovacion": " ",
        "EsRenovable": 0,
        "CodigoBIP": null,
        "Adjudicacion": null,
        "Items": {
          "Cantidad": 8,
          "Listado": [
            {
              "Correlativo": 1,
              "CodigoProducto": 42231609,
              "CodigoCategoria": "42231600",
              "Categoria": "Equipamiento y suministros médicos / Nutrición clínica / Accesorios o dispositivos de acceso de jejunostomía y gastrostomía",
              "NombreProducto": "Kits de tubos de alimentación por gastrostomía",
              "Descripcion": "224-1391 Set gastrostomia endoscopica 24 fr. Con sistema enfit",
              "UnidadMedida": "Kit",
              "Cantidad": 336,
              "Adjudicacion": null
            },
            {
              "Correlativo": 2,
              "CodigoProducto": 42142715,
              "CodigoCategoria": "42142700",
              "Categoria": "Equipamiento y suministros médicos / Suministros y productos clínicos / Suministros urológicos",
              "NombreProducto": "Kits de catéter urinario o accesorios",
              "Descripcion": "224-1625 Canastillo dormia 195cm,dm2cm",
              "UnidadMedida": "Unidad",
              "Cantidad": 148,
              "Adjudicacion": null
            },
            {
              "Correlativo": 3,
              "CodigoProducto": 42231609,
              "CodigoCategoria": "42231600",
              "Categoria": "Equipamiento y suministros médicos / Nutrición clínica / Accesorios o dispositivos de acceso de jejunostomía y gastrostomía",
              "NombreProducto": "Kits de tubos de alimentación por gastrostomía",
              "Descripcion": "224-1665 Set ligadura multidsparo 2 barriles",
              "UnidadMedida": "Kit",
              "Cantidad": 360,
              "Adjudicacion": null
            },
            {
              "Correlativo": 4,
              "CodigoProducto": 42142518,
              "CodigoCategoria": "42142500",
              "Categoria": "Equipamiento y suministros médicos / Suministros y productos clínicos / Agujas clínicas",
              "NombreProducto": "Productos de aspiración para biopsia o accesorios",
              "Descripcion": "224-7253 Pinza biopsia gastrica desechable",
              "UnidadMedida": "Unidad",
              "Cantidad": 240,
              "Adjudicacion": null
            },
            {
              "Correlativo": 5,
              "CodigoProducto": 42292601,
              "CodigoCategoria": "42292600",
              "Categoria": "Equipamiento y suministros médicos / Productos quirúrgicos / Dilatadores, sondas, ranuras quirúrgicas y productos relacionados",
              "NombreProducto": "Dilatadores quirúrgicos o accesorios",
              "Descripcion": "224-1538 Balon dilatacion esofagico l=7a8cm d=15a20mm",
              "UnidadMedida": "Unidad",
              "Cantidad": 8,
              "Adjudicacion": null
            },
            {
              "Correlativo": 6,
              "CodigoProducto": 42292601,
              "CodigoCategoria": "42292600",
              "Categoria": "Equipamiento y suministros médicos / Productos quirúrgicos / Dilatadores, sondas, ranuras quirúrgicas y productos relacionados",
              "NombreProducto": "Dilatadores quirúrgicos o accesorios",
              "Descripcion": "224-1539 Balon dilatacion esofagico l=5a6cm d=12a15mm",
              "UnidadMedida": "Unidad",
              "Cantidad": 8,
              "Adjudicacion": null
            },
            {
              "Correlativo": 7,
              "CodigoProducto": 42295137,
              "CodigoCategoria": "42295100",
              "Categoria": "Equipamiento y suministros médicos / Productos quirúrgicos / Equipo quirúrgico, accesorios y productos relacionados",
              "NombreProducto": "Equipo, suministros o accesorios de gastroenterología",
              "Descripcion": "224-1655 Papilotomo de punta triple lumen",
              "UnidadMedida": "Unidad",
              "Cantidad": 72,
              "Adjudicacion": null
            },
            {
              "Correlativo": 8,
              "CodigoProducto": 42271802,
              "CodigoCategoria": "42271800",
              "Categoria": "Equipamiento y suministros médicos / Productos de resucitación, anestesia y respiratorios / Productos para terapia respiratoria en aerosol y humidificación",
              "NombreProducto": "Nebulizadores o accesorios",
              "Descripcion": "224-1660 Papilotomo lateral triple lumen pta.redonda (dometip)",
              "UnidadMedida": "Unidad",
              "Cantidad": 240,
              "Adjudicacion": null
            }
          ]
        }
      }
    ]
  }
}