{
  "fuente": "mp",
  "query": "codigo=2263-62-LE26",
  "cacheado_en": 1783090464.424504,
  "payload": {
    "Cantidad": 1,
    "FechaCreacion": "2026-07-03T14:54:24.4682763Z",
    "Version": "v1",
    "Listado": [
      {
        "CodigoExterno": "2263-62-LE26",
        "Nombre": "ADQUISICIÓN DE ROLLOS PAPEL REFLECTANTE DIFERENTES COLORES PARA LOS TRABAJOS DE ADMINISTRACION DIRECTA DE LA DIRECCIÓN DE VIALIDAD PROVINCIA DE MALLECO CORRESPONDIENTE A LA UNIDAD PUENTE DE LA PROVINCIA DE MALLECO REGION DE LA ARAUCANIA",
        "CodigoEstado": 5,
        "Descripcion": "ADQUISICIÓN DE ROLLOS PAPEL REFLECTANTE DIFERENTES COLORES PARA LOS TRABAJOS DE ADMINISTRACION DIRECTA DE LA DIRECCIÓN DE VIALIDAD PROVINCIA DE MALLECO, CORRESPONDIENTE A LA UNIDAD PUENTE, DE LA PROVINCIA DE MALLECO, REGION DE LA ARAUCANIA",
        "FechaCierre": null,
        "Estado": "Publicada",
        "Comprador": {
          "CodigoOrganismo": "7248",
          "NombreOrganismo": "MINISTERIO DE OBRAS PUBLICAS DIREC CION GRAL DE OO PP DCYF",
          "RutUnidad": "61.202.000-0",
          "CodigoUnidad": "3257",
          "NombreUnidad": "Dirección de Vialidad - IX Región - Provincia de Malleco",
          "DireccionUnidad": "Lautaro 17",
          "ComunaUnidad": "Angol",
          "RegionUnidad": "Región de la Araucanía ",
          "RutUsuario": "",
          "CodigoUsuario": "2168240",
          "NombreUsuario": "PAOLA ANDREA VENEGAS ACUÑA",
          "CargoUsuario": "ANALISTA PRESUPUESTARIO VIALIDAD MALLECO"
        },
        "DiasCierreLicitacion": "7",
        "Informada": 0,
        "CodigoTipo": 1,
        "Tipo": "LE",
        "TipoConvocatoria": "1",
        "Moneda": "CLP",
        "Etapas": 1,
        "EstadoEtapas": "0",
        "TomaRazon": "0",
        "EstadoPublicidadOfertas": 1,
        "JustificacionPublicidad": "",
        "Contrato": "1",
        "Obras": "0",
        "CantidadReclamos": 459,
        "Fechas": {
          "FechaCreacion": "2026-06-23T00:00:00",
          "FechaCierre": "2026-07-10T16:39:00",
          "FechaInicio": "2026-06-30T23:11:00",
          "FechaFinal": "2026-07-02T23:11:00",
          "FechaPubRespuestas": "2026-07-03T23:12:00",
          "FechaActoAperturaTecnica": "2026-07-10T16:40:00",
          "FechaActoAperturaEconomica": "2026-07-10T16:40:00",
          "FechaPublicacion": "2026-06-30T23:06:27.523",
          "FechaAdjudicacion": "2026-07-17T16:40:00",
          "FechaEstimadaAdjudicacion": "2026-07-17T16:40:00",
          "FechaSoporteFisico": null,
          "FechaTiempoEvaluacion": null,
          "FechaEstimadaFirma": null,
          "FechasUsuario": null,
          "FechaVisitaTerreno": null,
          "FechaEntregaAntecedentes": null
        },
        "UnidadTiempoEvaluacion": 1,
        "DireccionVisita": "",
        "DireccionEntrega": "",
        "Estimacion": 1,
        "FuenteFinanciamiento": "PROG. 234",
        "VisibilidadMonto": 0,
        "MontoEstimado": null,
        "Tiempo": null,
        "UnidadTiempo": "1",
        "Modalidad": 1,
        "TipoPago": "1",
        "NombreResponsablePago": "PAOLA VENEGAS ACUÑA",
        "EmailResponsablePago": "",
        "NombreResponsableContrato": "CARLOS BARROS SAEZ",
        "EmailResponsableContrato": "",
        "FonoResponsableContrato": "",
        "ProhibicionContratacion": "Se prohibe la subcontratación",
        "SubContratacion": "0",
        "UnidadTiempoDuracionContrato": 1,
        "TiempoDuracionContrato": "0",
        "TipoDuracionContrato": " ",
        "JustificacionMontoEstimado": "ESTIMADO PRECIO DE MERCADO",
        "ObservacionContract": null,
        "ExtensionPlazo": 0,
        "EsBaseTipo": 0,
        "UnidadTiempoContratoLicitacion": "1",
        "ValorTiempoRenovacion": "0",
        "PeriodoTiempoRenovacion": " ",
        "EsRenovable": 0,
        "CodigoBIP": null,
        "Adjudicacion": null,
        "Items": {
          "Cantidad": 11,
          "Listado": [
            {
              "Correlativo": 1,
              "CodigoProducto": 31201516,
              "CodigoCategoria": "31201500",
              "Categoria": "Artículos de fabricación y producción / Cintas adhesivas y selladores / Cinta adhesiva",
              "NombreProducto": "Cinta reflectiva",
              "Descripcion": "PAPEL MATE NEGRO (0,60 CM. ANCHO)",
              "UnidadMedida": "Rollo",
              "Cantidad": 15,
              "Adjudicacion": null
            },
            {
              "Correlativo": 2,
              "CodigoProducto": 31201516,
              "CodigoCategoria": "31201500",
              "Categoria": "Artículos de fabricación y producción / Cintas adhesivas y selladores / Cinta adhesiva",
              "NombreProducto": "Cinta reflectiva",
              "Descripcion": "PAPEL REFLECTANTE MATE BLANCO Gº INGENIERIA (0,60 CM. ANCHO)",
              "UnidadMedida": "Rollo",
              "Cantidad": 7,
              "Adjudicacion": null
            },
            {
              "Correlativo": 3,
              "CodigoProducto": 31201516,
              "CodigoCategoria": "31201500",
              "Categoria": "Artículos de fabricación y producción / Cintas adhesivas y selladores / Cinta adhesiva",
              "NombreProducto": "Cinta reflectiva",
              "Descripcion": "PAPEL REFLECTANTE AMARILLO Gº ALTA INTENSIDAD (0,60 CM. ANCHO)",
              "UnidadMedida": "Rollo",
              "Cantidad": 5,
              "Adjudicacion": null
            },
            {
              "Correlativo": 4,
              "CodigoProducto": 31201516,
              "CodigoCategoria": "31201500",
              "Categoria": "Artículos de fabricación y producción / Cintas adhesivas y selladores / Cinta adhesiva",
              "NombreProducto": "Cinta reflectiva",
              "Descripcion": "PAPEL REFLECTANTE ROJO Gº ALTA INTENSIDAD (0,60 CM. ANCHO)",
              "UnidadMedida": "Rollo",
              "Cantidad": 3,
              "Adjudicacion": null
            },
            {
              "Correlativo": 5,
              "CodigoProducto": 31201516,
              "CodigoCategoria": "31201500",
              "Categoria": "Artículos de fabricación y producción / Cintas adhesivas y selladores / Cinta adhesiva",
              "NombreProducto": "Cinta reflectiva",
              "Descripcion": "PAPEL REFLECTANTE CAFE Gº ALTA INTENSIDAD (0,60 CM. ANCHO)",
              "UnidadMedida": "Rollo",
              "Cantidad": 2,
              "Adjudicacion": null
            },
            {
              "Correlativo": 6,
              "CodigoProducto": 31201516,
              "CodigoCategoria": "31201500",
              "Categoria": "Artículos de fabricación y producción / Cintas adhesivas y selladores / Cinta adhesiva",
              "NombreProducto": "Cinta reflectiva",
              "Descripcion": "PAPEL REFLECTANTE NARANJO Gº ALTA INTENSIDAD (0,60 CM. ANCHO)",
              "UnidadMedida": "Rollo",
              "Cantidad": 2,
              "Adjudicacion": null
            },
            {
              "Correlativo": 7,
              "CodigoProducto": 31201516,
              "CodigoCategoria": "31201500",
              "Categoria": "Artículos de fabricación y producción / Cintas adhesivas y selladores / Cinta adhesiva",
              "NombreProducto": "Cinta reflectiva",
              "Descripcion": "PAPEL REFLECTANTE VERDE Gº ALTA INTENSIDAD (0,60 CM. ANCHO)",
              "UnidadMedida": "Rollo",
              "Cantidad": 3,
              "Adjudicacion": null
            },
            {
              "Correlativo": 8,
              "CodigoProducto": 31201516,
              "CodigoCategoria": "31201500",
              "Categoria": "Artículos de fabricación y producción / Cintas adhesivas y selladores / Cinta adhesiva",
              "NombreProducto": "Cinta reflectiva",
              "Descripcion": "PAPEL REFLECTANTE AZUL Gº ALTA INTENSIDAD (0,60 CM. ANCHO)",
              "UnidadMedida": "Rollo",
              "Cantidad": 2,
              "Adjudicacion": null
            },
            {
              "Correlativo": 9,
              "CodigoProducto": 31201516,
              "CodigoCategoria": "31201500",
              "Categoria": "Artículos de fabricación y producción / Cintas adhesivas y selladores / Cinta adhesiva",
              "NombreProducto": "Cinta reflectiva",
              "Descripcion": "PAPEL REFLECTANTE NARANJO Gº DIAMANTE FLUOR (0,60 CM. ANCHO)",
              "UnidadMedida": "Rollo",
              "Cantidad": 2,
              "Adjudicacion": null
            },
            {
              "Correlativo": 10,
              "CodigoProducto": 31201516,
              "CodigoCategoria": "31201500",
              "Categoria": "Artículos de fabricación y producción / Cintas adhesivas y selladores / Cinta adhesiva",
              "NombreProducto": "Cinta reflectiva",
              "Descripcion": "PAPEL REFLECTANTE AMARILLO-VERDE LIMON FLUOR Gº ALTA DIAMANTE (0,60 CM. ANCHO)",
              "UnidadMedida": "Rollo",
              "Cantidad": 4,
              "Adjudicacion": null
            },
            {
              "Correlativo": 11,
              "CodigoProducto": 31201516,
              "CodigoCategoria": "31201500",
              "Categoria": "Artículos de fabricación y producción / Cintas adhesivas y selladores / Cinta adhesiva",
              "NombreProducto": "Cinta reflectiva",
              "Descripcion": "LOGOS MONOCROMATICO BLANCO REFLECTANTE Y LETRAS NEGRAS 12 CM., DIAMETRO (IMAGEN REFERENCIAL)",
              "UnidadMedida": "Unidad",
              "Cantidad": 6000,
              "Adjudicacion": null
            }
          ]
        }
      }
    ]
  }
}