{
  "fuente": "mp",
  "query": "codigo=1057509-131-LE26",
  "cacheado_en": 1783055854.809737,
  "payload": {
    "Cantidad": 1,
    "FechaCreacion": "2026-07-03T05:17:34.8916004Z",
    "Version": "v1",
    "Listado": [
      {
        "CodigoExterno": "1057509-131-LE26",
        "Nombre": "CONVENIO MANTENCIÓN PREVENTIVA Y CORRECTIVA DE SISTEMA VIDEO VIGILANCIA Y ALARMA DE SEGURIDAD PROVEEDURÍA E INSTALACIÓN DE CÁMARAS DE SEGURIDAD Y SISTEMA DE ALARMAS DE SEGURIDAD SIN MONITOREO",
        "CodigoEstado": 5,
        "Descripcion": "El Hospital Clínico Herminda Martin de Chillán requiere efectuar licitación pública para la contratación del “CONVENIO MANTENCIÓN PREVENTIVA Y CORRECTIVA DE SISTEMA VIDEO VIGILANCIA Y ALARMA DE SEGURIDAD; PROVEEDURÍA E INSTALACIÓN DE CÁMARAS DE SEGURIDAD Y SISTEMA DE ALARMAS DE SEGURIDAD SIN MONITOREO”, de esta forma entregar seguridad a los pacientes y funcionarios del HCHM, proporcionando una red de cámaras de seguridad y sistema de alarma, en puntos estratégicos de las instalaciones, así mantener un respaldo y registro del actuar diario de todas las personas que asisten a las instalaciones, esto de acuerdo a las exigencias descritas en las presentes especificaciones técnicas y en general, de conformidad a las normas vigentes sobre la materia.",
        "FechaCierre": null,
        "Estado": "Publicada",
        "Comprador": {
          "CodigoOrganismo": "7042",
          "NombreOrganismo": "HOSPITAL CLINICO HERMINDA MARTIN",
          "RutUnidad": "61.607.001-0",
          "CodigoUnidad": "1057509",
          "NombreUnidad": "Bienes y Servicios",
          "DireccionUnidad": "Francisco Ramirez N°10",
          "ComunaUnidad": "Chillán",
          "RegionUnidad": "Región del Ñuble",
          "RutUsuario": "",
          "CodigoUsuario": "1703367",
          "NombreUsuario": "FELIPE GELDRES",
          "CargoUsuario": "Ejecutivo de Licitaciones y Convenios"
        },
        "DiasCierreLicitacion": "10",
        "Informada": 0,
        "CodigoTipo": 1,
        "Tipo": "LE",
        "TipoConvocatoria": "1",
        "Moneda": "CLP",
        "Etapas": 1,
        "EstadoEtapas": "0",
        "TomaRazon": "0",
        "EstadoPublicidadOfertas": 1,
        "JustificacionPublicidad": "",
        "Contrato": "1",
        "Obras": "0",
        "CantidadReclamos": 1493,
        "Fechas": {
          "FechaCreacion": "2026-05-27T00:00:00",
          "FechaCierre": "2026-07-13T15:00:00",
          "FechaInicio": "2026-07-02T17:01:00",
          "FechaFinal": "2026-07-07T17:30:00",
          "FechaPubRespuestas": "2026-07-08T17:30:00",
          "FechaActoAperturaTecnica": "2026-07-13T15:01:00",
          "FechaActoAperturaEconomica": "2026-07-13T15:01:00",
          "FechaPublicacion": "2026-07-02T16:34:28.927",
          "FechaAdjudicacion": "2026-07-31T16:00:00",
          "FechaEstimadaAdjudicacion": "2026-07-31T16:00:00",
          "FechaSoporteFisico": null,
          "FechaTiempoEvaluacion": null,
          "FechaEstimadaFirma": null,
          "FechasUsuario": "1900-01-02T00:00:00",
          "FechaVisitaTerreno": null,
          "FechaEntregaAntecedentes": null
        },
        "UnidadTiempoEvaluacion": 1,
        "DireccionVisita": "",
        "DireccionEntrega": "",
        "Estimacion": 2,
        "FuenteFinanciamiento": "",
        "VisibilidadMonto": 1,
        "MontoEstimado": 3519857,
        "Tiempo": "6",
        "UnidadTiempo": "1",
        "Modalidad": 1,
        "TipoPago": "1",
        "NombreResponsablePago": "Tesorería General de la República",
        "EmailResponsablePago": "",
        "NombreResponsableContrato": "",
        "EmailResponsableContrato": "",
        "FonoResponsableContrato": "",
        "ProhibicionContratacion": "",
        "SubContratacion": "1",
        "UnidadTiempoDuracionContrato": 4,
        "TiempoDuracionContrato": "6",
        "TipoDuracionContrato": " ",
        "JustificacionMontoEstimado": "",
        "ObservacionContract": null,
        "ExtensionPlazo": 0,
        "EsBaseTipo": 0,
        "UnidadTiempoContratoLicitacion": "2",
        "ValorTiempoRenovacion": "0",
        "PeriodoTiempoRenovacion": " ",
        "EsRenovable": 0,
        "CodigoBIP": null,
        "Adjudicacion": null,
        "Items": {
          "Cantidad": 1,
          "Listado": [
            {
              "Correlativo": 1,
              "CodigoProducto": 41115807,
              "CodigoCategoria": "41115800",
              "Categoria": "Equipamiento para laboratorios / Instrumentos de medida y experimentación / Analizadores, accesorios y suministros clínicos y de diagnósticos",
              "NombreProducto": "Analizadores químicos",
              "Descripcion": "Proveeduría y Mantención de Cámaras de Seguridad, Presupuesto $ 3.519.857. Ofertar de según Anexo N°3 \"Oferta Económica\"",
              "UnidadMedida": "Unidad no definida",
              "Cantidad": 1,
              "Adjudicacion": null
            }
          ]
        }
      }
    ]
  }
}