{
  "fuente": "mp",
  "query": "codigo=2445-90-L126",
  "cacheado_en": 1783090675.313787,
  "payload": {
    "Cantidad": 1,
    "FechaCreacion": "2026-07-03T14:57:55.3430996Z",
    "Version": "v1",
    "Listado": [
      {
        "CodigoExterno": "2445-90-L126",
        "Nombre": "SERVICIO DE  LENTES OPTICOS  NIÑOS Y NIÑAS C-CORRECCION DE VICIOS DE REFRACCION ",
        "CodigoEstado": 5,
        "Descripcion": "POR SERVICIO DE  LENTES OPTICOS  NIÑOS Y NIÑAS C-CORRECCION DE VICIOS DE REFRACCION ",
        "FechaCierre": null,
        "Estado": "Publicada",
        "Comprador": {
          "CodigoOrganismo": "87838",
          "NombreOrganismo": "I MUNICIPALIDAD DE CURICO",
          "RutUnidad": "69.100.100-8",
          "CodigoUnidad": "3437",
          "NombreUnidad": "Salud - Adquisiciones",
          "DireccionUnidad": "VILLA SANTA ELENA S/N, LOS NICHES",
          "ComunaUnidad": "Curicó",
          "RegionUnidad": "Región del Maule ",
          "RutUsuario": "",
          "CodigoUsuario": "167599",
          "NombreUsuario": "Lucila Karin  CUBILLOS CARRERA",
          "CargoUsuario": "TECNICO"
        },
        "DiasCierreLicitacion": "10",
        "Informada": 0,
        "CodigoTipo": 1,
        "Tipo": "L1",
        "TipoConvocatoria": "1",
        "Moneda": "CLP",
        "Etapas": 1,
        "EstadoEtapas": "0",
        "TomaRazon": "0",
        "EstadoPublicidadOfertas": 1,
        "JustificacionPublicidad": "Todas las ofertas técnicas serán visibles al público en general, través del portal www.mercadopublico.cl, desde el momento de la apertura electrónica.",
        "Contrato": "0",
        "Obras": "0",
        "CantidadReclamos": 1057,
        "Fechas": {
          "FechaCreacion": "2026-06-24T11:53:24.603",
          "FechaCierre": "2026-07-13T20:00:00",
          "FechaInicio": "2026-06-26T16:28:40.36",
          "FechaFinal": "2026-07-03T20:00:00",
          "FechaPubRespuestas": "2026-07-06T15:00:00",
          "FechaActoAperturaTecnica": "2026-07-13T20:01:00",
          "FechaActoAperturaEconomica": "2026-07-13T20:01:00",
          "FechaPublicacion": "2026-06-26T16:28:40.36",
          "FechaAdjudicacion": "2026-08-11T17:00:00",
          "FechaEstimadaAdjudicacion": "2026-08-11T17:00:00",
          "FechaSoporteFisico": null,
          "FechaTiempoEvaluacion": null,
          "FechaEstimadaFirma": null,
          "FechasUsuario": null,
          "FechaVisitaTerreno": null,
          "FechaEntregaAntecedentes": null
        },
        "UnidadTiempoEvaluacion": 2,
        "DireccionVisita": "",
        "DireccionEntrega": "",
        "Estimacion": 2,
        "FuenteFinanciamiento": "",
        "VisibilidadMonto": 1,
        "MontoEstimado": 5355000,
        "Tiempo": null,
        "UnidadTiempo": "2",
        "Modalidad": 0,
        "TipoPago": "-1",
        "NombreResponsablePago": "",
        "EmailResponsablePago": "",
        "NombreResponsableContrato": "",
        "EmailResponsableContrato": "",
        "FonoResponsableContrato": "",
        "ProhibicionContratacion": "",
        "SubContratacion": "1",
        "UnidadTiempoDuracionContrato": 0,
        "TiempoDuracionContrato": "0",
        "TipoDuracionContrato": " ",
        "JustificacionMontoEstimado": "1",
        "ObservacionContract": null,
        "ExtensionPlazo": 1,
        "EsBaseTipo": 0,
        "UnidadTiempoContratoLicitacion": "0",
        "ValorTiempoRenovacion": "0",
        "PeriodoTiempoRenovacion": " ",
        "EsRenovable": 0,
        "CodigoBIP": null,
        "Adjudicacion": null,
        "Items": {
          "Cantidad": 1,
          "Listado": [
            {
              "Correlativo": 1,
              "CodigoProducto": 31241501,
              "CodigoCategoria": "31241500",
              "Categoria": "Artículos de fabricación y producción / Óptica industrial / Lentes y prismas industriales",
              "NombreProducto": "Lentes",
              "Descripcion": "Servicio de provisión de lentes ópticos con corrección de vicios de refracción para niños y niñas, usuarios entre 8 y 13 años de edad, pertenecientes a la comuna de Curicó,\n\n",
              "UnidadMedida": "Unidad",
              "Cantidad": 250,
              "Adjudicacion": null
            }
          ]
        }
      }
    ]
  }
}