{
  "fuente": "mp",
  "query": "codigo=1057491-131-LP26",
  "cacheado_en": 1783055803.6125271,
  "payload": {
    "Cantidad": 1,
    "FechaCreacion": "2026-07-03T05:16:43.6885164Z",
    "Version": "v1",
    "Listado": [
      {
        "CodigoExterno": "1057491-131-LP26",
        "Nombre": "SUMINISTRO DE STENT HEMODINAMIA",
        "CodigoEstado": 5,
        "Descripcion": "ADQUISICIÓN, POR SISTEMA DE SUMINISTRO DE STENT HEMODINAMIA, PARA EL HOSPITAL DOCTOR LUIS CALVO MACKENNA",
        "FechaCierre": null,
        "Estado": "Publicada",
        "Comprador": {
          "CodigoOrganismo": "6918",
          "NombreOrganismo": "SERVICIO DE SALUD ORIENTE HOSPITAL LUIS CALVO MACKENNA",
          "RutUnidad": "61.608.408-9",
          "CodigoUnidad": "1057491",
          "NombreUnidad": "Bienes y Servicios",
          "DireccionUnidad": "ANTONIO VARAS 360 (CENTRO DE DISTRIBUCIÓN)",
          "ComunaUnidad": "Providencia",
          "RegionUnidad": "Región Metropolitana de Santiago",
          "RutUsuario": "",
          "CodigoUsuario": "1845146",
          "NombreUsuario": "MAXIMILIANO LEON",
          "CargoUsuario": "Analista de Licitaciones"
        },
        "DiasCierreLicitacion": "10",
        "Informada": 0,
        "CodigoTipo": 1,
        "Tipo": "LP",
        "TipoConvocatoria": "1",
        "Moneda": "CLP",
        "Etapas": 1,
        "EstadoEtapas": "0",
        "TomaRazon": "0",
        "EstadoPublicidadOfertas": 1,
        "JustificacionPublicidad": "",
        "Contrato": "0",
        "Obras": "0",
        "CantidadReclamos": 1047,
        "Fechas": {
          "FechaCreacion": "2026-06-19T13:20:57.24",
          "FechaCierre": "2026-07-13T15:00:00",
          "FechaInicio": "2026-06-22T15:01:00",
          "FechaFinal": "2026-06-30T15:00:00",
          "FechaPubRespuestas": "2026-07-03T20:00:00",
          "FechaActoAperturaTecnica": "2026-07-13T15:01:00",
          "FechaActoAperturaEconomica": "2026-07-13T15:01:00",
          "FechaPublicacion": "2026-06-22T10:58:16.337",
          "FechaAdjudicacion": "2026-07-31T15:00:00",
          "FechaEstimadaAdjudicacion": "2026-07-31T15:00:00",
          "FechaSoporteFisico": null,
          "FechaTiempoEvaluacion": null,
          "FechaEstimadaFirma": null,
          "FechasUsuario": null,
          "FechaVisitaTerreno": null,
          "FechaEntregaAntecedentes": null
        },
        "UnidadTiempoEvaluacion": 1,
        "DireccionVisita": "",
        "DireccionEntrega": "",
        "Estimacion": 1,
        "FuenteFinanciamiento": "HOSPITAL LUIS CALVO MACKENNA",
        "VisibilidadMonto": 0,
        "MontoEstimado": null,
        "Tiempo": "24",
        "UnidadTiempo": "1",
        "Modalidad": 1,
        "TipoPago": "1",
        "NombreResponsablePago": "BARBARA SALINAS",
        "EmailResponsablePago": "",
        "NombreResponsableContrato": "MAXIMILIANO LEON",
        "EmailResponsableContrato": "",
        "FonoResponsableContrato": "",
        "ProhibicionContratacion": "",
        "SubContratacion": "0",
        "UnidadTiempoDuracionContrato": 4,
        "TiempoDuracionContrato": "24",
        "TipoDuracionContrato": " ",
        "JustificacionMontoEstimado": "",
        "ObservacionContract": null,
        "ExtensionPlazo": 0,
        "EsBaseTipo": 0,
        "UnidadTiempoContratoLicitacion": "2",
        "ValorTiempoRenovacion": "0",
        "PeriodoTiempoRenovacion": " ",
        "EsRenovable": 0,
        "CodigoBIP": null,
        "Adjudicacion": null,
        "Items": {
          "Cantidad": 3,
          "Listado": [
            {
              "Correlativo": 1,
              "CodigoProducto": 42142604,
              "CodigoCategoria": "42142600",
              "Categoria": "Equipamiento y suministros médicos / Suministros y productos clínicos / Jeringas y accesorios",
              "NombreProducto": "Jeringas médicas con casquillo de catéter",
              "Descripcion": "212-0166 - STENT CORONARIO ALEACIÓN ACERO, PLATINO Y CROMO.\tCON MEDICAMENTO EVEROLIMUS, MEDIDAS 2,25-5,0 MM",
              "UnidadMedida": "Unidad",
              "Cantidad": 40,
              "Adjudicacion": null
            },
            {
              "Correlativo": 2,
              "CodigoProducto": 42142604,
              "CodigoCategoria": "42142600",
              "Categoria": "Equipamiento y suministros médicos / Suministros y productos clínicos / Jeringas y accesorios",
              "NombreProducto": "Jeringas médicas con casquillo de catéter",
              "Descripcion": "212-0045 - STENT PERIFÉRICO DE ACERO INOXIDABLE NO PREMONTADO, \tFABRICADO DE 1 PIEZA CORTADO POR LÁSER, DISEÑO DE CELDAS CERRADAS CON SEGMENTOS EN S PARA FLEXIBILIDAD, DIÁMETROS 10-12 MM, LONGITUD 19, 29, 39, 40, 50 Y 59 MM",
              "UnidadMedida": "Unidad",
              "Cantidad": 40,
              "Adjudicacion": null
            },
            {
              "Correlativo": 3,
              "CodigoProducto": 42142604,
              "CodigoCategoria": "42142600",
              "Categoria": "Equipamiento y suministros médicos / Suministros y productos clínicos / Jeringas y accesorios",
              "NombreProducto": "Jeringas médicas con casquillo de catéter",
              "Descripcion": "212-0044 - STENT CORONARIO ALEACIÓN ACERO, PLATINO Y CROMO.\tCON MEDICAMENTO EVEROLIMUS, MEDIDAS 3,5-5,0 MM. SOBRE-DILATABLE HASTA 6,0 MM",
              "UnidadMedida": "Unidad",
              "Cantidad": 20,
              "Adjudicacion": null
            }
          ]
        }
      }
    ]
  }
}